{"stat.chestOpened":9,"stat.walkOneCm":67927,"stat.drop.minecraft.stone_brick_stairs":2,"stat.leaveGame":3,"stat.useItem.minecraft.log":2,"stat.craftItem.minecraft.crafting_table":1,"stat.furnaceInteraction":2,"stat.mineBlock.srparasites.gore":2,"stat.pickup.minecraft.log":11,"stat.pickup.minecraft.stone_brick_stairs":2,"stat.killEntity.wasp":2,"stat.jump":772,"stat.swimOneCm":2216,"stat.pickup.minecraft.coal":2,"stat.pickup.minecraft.cooked_chicken":2,"stat.climbOneCm":1444,"stat.fallOneCm":14547,"stat.useItem.minecraft.planks":5,"stat.pickup.minecraft.furnace":1,"stat.pickup.minecraft.chicken":1,"stat.crouchOneCm":783,"stat.pickup.minecraft.sapling":4,"stat.sprintOneCm":104955,"stat.useItem.minecraft.stone_slab2":5,"stat.pickup.minecraft.apple":1,"stat.useItem.minecraft.cooked_chicken":1,"stat.craftingTableInteraction":1,"stat.craftItem.minecraft.planks":36,"stat.useItem.minecraft.egg":8,"stat.damageTaken":3997,"stat.useItem.futuremc.sweet_berries":10,"stat.mobKills":5,"stat.mineBlock.minecraft.log":11,"stat.pickup.minecraft.planks":5,"stat.pickup.futuremc.sweet_berries":60,"stat.flyOneCm":465436,"stat.deaths":13,"stat.mineBlock.minecraft.planks":5,"stat.drop":3,"stat.pickup.minecraft.wheat_seeds":1,"stat.pickup.minecraft.egg":9,"stat.mineBlock.minecraft.leaves":2,"stat.playOneMinute":50561,"stat.entityKilledBy.Zombie":1,"stat.entityKilledBy.Silverfish":1,"stat.pickup.spartanweaponry.caestus":1,"stat.killEntity.Sheep":1,"stat.sneakTime":383,"stat.pickup.minecraft.wool":1,"stat.damageDealt":261,"stat.timeSinceDeath":17889,"stat.drop.spartanweaponry.caestus":1,"stat.killEntity.Cow":1,"stat.useItem.minecraft.spawn_egg":23,"stat.mineBlock.minecraft.tallgrass":3,"stat.diveOneCm":493,"stat.pickup.minecraft.mutton":2}